{
  "required": true,
  "minVersion": "0.8",
  "package": "net.rpgdifficulty.mixin",
  "compatibilityLevel": "JAVA_17",
  "mixins": [
    "ZombieEntityMixin",
    "AbstractSkeletonEntityMixin",
    "MobEntityMixin",
    "WitherSkullBlockMixin",
    "EnderDragonFightMixin",
    "PassiveEntityMixin",
    "CreeperEntityMixin",
    "LivingEntityMixin",
    "ServerWorldMixin"
  ],
  "client": [
    "client.ZombieBaseEntityRendererMixin",
    "client.InGameHudMixin",
    "client.ScreenMixin"
  ],
  "injectors": {
    "defaultRequire": 1
  }
}